{
 "summary":[
{"Sell Out": "1.99M" , "status":"up"},
{"Achievement": "49%","status":"down"},
{"ASO": "127K" , "status":"equal"},
{"VPO": "12M", "status":"down"},
{"SellOutperDistributor": "2M","status":"up"}
],

 "MultipleBaChartData": {
 "name": "MultipleBaChartData-TOTAL REVENUE",
 "Title": "Sell out by Year",
 "MultipleBaChartData": [
    { "interval": "2019", "service": "Foods", "value": "12","intervalID": "" ,"serviceID":"" },
    { "interval": "2020", "service": "Foods", "value": "15","intervalID": "","serviceID":""  },
    { "interval": "2019", "service": "Beverage", "value": "8","intervalID": "" ,"serviceID":"" },
    { "interval": "2020", "service": "Beverage", "value": "15","intervalID": "" ,"serviceID":"" },
    { "interval": "January",  "service": "Short Eats", "value": "5","intervalID": "2019" ,"serviceID":"Foods" },
    { "interval": "January", "service": "Shakes", "value": "12","intervalID": "2019" ,"serviceID":"Beverage" },
    { "interval": "January", "service": "Alcohol", "value": "6","intervalID": "2019" ,"serviceID":"Beverage" },
    { "interval": "January",  "service": "Short Eats", "value": "10","intervalID": "2020" ,"serviceID":"Foods" },
    { "interval": "January",  "service": "Shakes", "value": "1","intervalID": "2020" ,"serviceID":"Beverage" },
    { "interval": "January", "service": "Chocolate Shake", "value": "5","intervalID": "January" ,"serviceID":"Shakes" }
    ]
  
 },

"pieData": {
 "name": "Sellout By Product Category",
 "Title": "Sellout By Product Category",
 "pieData": [{ "kind": "Beverage", "share": "0.175", "parentID": "" },
    { "kind": "Cake", "share": "0.238","parentID": "" },
    { "kind": "Jams", "share": "0.118","parentID": "" },
    { "kind": "Biscuits", "share": "0.052","parentID": "" },
    { "kind": "Juices", "share": "0.225","parentID": "Beverage" },
    { "kind": "Nectar", "share": "0.192","parentID": "Beverage" },
    { "kind": "coke", "share": "0.192","parentID": "Beverage" },
    { "kind": "wafers", "share": "0.225","parentID": "Biscuits" },
    { "kind": "Choky", "share": "0.192","parentID": "Biscuits" }
    ]

},

 "lineBarData":{
 "name": "Sell out Trending - 2021",
 "Title": "Sell out Trending - 2021",
  "categories": [2002, 2003, 2004, 2005, 2006],
 "data":[{
    "name": "Foods",
    "type":"line",
    "data": [3.907, 5.943, 4.848, 3.284, 5.263]
  }, {
    "name": "Beverages",
    "type":"bar",
    "data": [4.743, 7.295, 7.175, 6.376, 8.153]
  }]
  
 },
 
 
 "lineBar":{
 "name": "Sell out Trending - 2021",
 "Title": "Sell out Trending - 2021",
 "line": [
     { "category": "2002", "service": "Foods", "value": "3.9","categoryID":"", "serviceID":""},
                  { "category": "Jan",  "service": "Foods", "value": "5","categoryID":"2002", "serviceID":"Foods"},
                  { "category": "Feb",  "service": "Foods", "value": "6","categoryID":"2002", "serviceID":"Foods"},
     { "category": "2003", "service": "Foods", "value": "5.9","categoryID":"", "serviceID":""},
                  { "category": "Jan",  "service": "Foods", "value": "7","categoryID":"2003", "serviceID":"Foods"},
                  { "category": "Feb", "service": "Foods", "value": "3","categoryID":"2003", "serviceID":"Foods"},
     { "category": "2004",  "service": "Foods", "value": "4.8","categoryID":"", "serviceID":""},
     { "category": "2005",  "service": "Foods", "value": "3.2","categoryID":"", "serviceID":""}],
     
"bar":[{ "category": "2002",  "service": "Beverage", "value": "4.7","categoryID":"", "serviceID":""},
                  { "category": "Jan",  "service": "Beverage", "value": "9","categoryID":"2002", "serviceID":"Beverage"},
                  { "category": "Feb",  "service": "Beverage", "value": "9","categoryID":"2002", "serviceID":"Beverage"},
     { "category": "2003", "service": "Beverage", "value": "7.2","categoryID":"", "serviceID":""},
                  { "category": "Jan",  "service": "Beverage", "value": "2","categoryID":"2003", "serviceID":"Beverage"},
                  { "category": "Feb",  "service": "Beverage", "value": "8","categoryID":"2003", "serviceID":"Beverage"},
     { "category": "2004", "service": "Beverage", "value": "7.1","categoryID":"", "serviceID":""},
     { "category": "2005",  "service": "Beverage", "value": "6.3","categoryID":"", "serviceID":""}
    ]
  
 }
}
